v1pysdk/__init__.py
v1pysdk/base_asset.py
v1pysdk/cache_decorator.py
v1pysdk/client.py
v1pysdk/none_deref.py
v1pysdk/query.py
v1pysdk/special_class_methods.py
v1pysdk/string_utils.py
v1pysdk/v1meta.py
v1pysdk/v1poll.py
v1pysdk/yamlquery.py
v1pysdk-0.6.2.dist-info/METADATA
v1pysdk-0.6.2.dist-info/RECORD
v1pysdk-0.6.2.dist-info/WHEEL
v1pysdk-0.6.2.dist-info/top_level.txt
