Metadata-Version: 2.1
Name: v1pysdk
Version: 0.6.2
Summary: VersionOne API client
Home-page: http://github.com/mtalexan/VersionOne.SDK.Python.git
Author: Joe Koberg (VersionOne, Inc.)
Author-email: Joe.Koberg@versionone.com
License: MIT/BSD
Project-URL: Source, http://github.com/mtalexan/VersionOne.SDK.Python.git
Project-URL: Tracker, http://github.com/mtalexan/VersionOne.SDK.Python.git/issues
Project-URL: Documentation, http://github.com/mtalexan/VersionOne.SDK.Python.git
Keywords: versionone v1 api sdk
Platform: UNKNOWN
Classifier: Development Status :: 4 - Beta
Classifier: Intended Audience :: Developers
Classifier: License :: OSI Approved :: MIT License
Classifier: License :: OSI Approved :: BSD License
Classifier: Operating System :: OS Independent
Classifier: Programming Language :: Python :: 2
Classifier: Programming Language :: Python :: 2.7
Classifier: Programming Language :: Python :: 3
Classifier: Programming Language :: Python :: 3.5
Classifier: Topic :: Software Development :: Bug Tracking
Requires-Python: >=2.5, <4
Requires-Dist: future
Requires-Dist: python-ntlm3
